fdet/__init__.py
fdet/detector.py
fdet/mtcnn.py
fdet/retinaface.py
fdet/cli/__init__.py
fdet/cli/main.py
fdet/utils/__init__.py
fdet/utils/errors.py
fdet/utils/io.py
fdet_offline-1.0.5.dist-info/LICENSE
fdet_offline-1.0.5.dist-info/METADATA
fdet_offline-1.0.5.dist-info/WHEEL
fdet_offline-1.0.5.dist-info/entry_points.txt
fdet_offline-1.0.5.dist-info/top_level.txt
fdet_offline-1.0.5.dist-info/RECORD
