Metadata-Version: 2.1
Name: fdet-offline
Version: 1.0.5
Summary: An easy to use face detection module based on MTCNN and RetinaFace algorithms.
Home-page: https://github.com/vikrosj/fdet-offline
Author: Viktoria R.
Author-email: viktoria.rosjo@gmail.com
Maintainer: Viktoria R.
Maintainer-email: viktoria.rosjo@gmail.com
License: UNKNOWN
Download-URL: https://github.com/vikrosj/fdet-offline/archive/1.0.5.tar.gz
Keywords: face recognition detection biometry
Platform: UNKNOWN
Requires-Python: >=3.8
Requires-Dist: CacheControl (==0.12.6)
Requires-Dist: Pillow (==8.0.0)
Requires-Dist: appdirs (==1.4.3)
Requires-Dist: attrs (==20.2.0)
Requires-Dist: certifi (==2019.11.28)
Requires-Dist: chardet (==3.0.4)
Requires-Dist: click (==7.1.2)
Requires-Dist: colorama (==0.4.4)
Requires-Dist: colour (==0.1.5)
Requires-Dist: contextlib2 (==0.6.0)
Requires-Dist: distlib (==0.3.0)
Requires-Dist: distro (==1.4.0)
Requires-Dist: fdet-offline-mtcnn-weights (==1.0.0)
Requires-Dist: future (==0.18.2)
Requires-Dist: html5lib (==1.0.1)
Requires-Dist: idna (==2.8)
Requires-Dist: iniconfig (==1.1.1)
Requires-Dist: ipaddr (==2.2.0)
Requires-Dist: lockfile (==0.12.2)
Requires-Dist: msgpack (==0.6.2)
Requires-Dist: numpy (==1.19.2)
Requires-Dist: opencv-python (==4.4.0.44)
Requires-Dist: packaging (==20.3)
Requires-Dist: pep517 (==0.8.2)
Requires-Dist: pluggy (==0.13.1)
Requires-Dist: progress (==1.5)
Requires-Dist: py (==1.9.0)
Requires-Dist: pyparsing (==2.4.6)
Requires-Dist: pytest (==6.1.1)
Requires-Dist: pytoml (==0.1.21)
Requires-Dist: requests (==2.22.0)
Requires-Dist: retrying (==1.3.3)
Requires-Dist: six (==1.14.0)
Requires-Dist: toml (==0.10.1)
Requires-Dist: torch (==1.6.0+cpu)
Requires-Dist: torchvision (==0.7.0+cpu)
Requires-Dist: ttictoc (==0.5.6)
Requires-Dist: urllib3 (==1.25.8)
Requires-Dist: webencodings (==0.5.1)
